pycompilerx/__init__.py
pycompilerx/cli.py
pycompilerx/py.typed
pycompilerx/analysis/__init__.py
pycompilerx/analysis/type_check.py
pycompilerx/backend/__init__.py
pycompilerx/backend/cython.py
pycompilerx/backend/llvm.py
pycompilerx/backend/numba.py
pycompilerx/examples/__init__.py
pycompilerx/examples/ast_transform.py
pycompilerx/examples/basic_calc.py
pycompilerx/parsing/__init__.py
pycompilerx/parsing/ast_tools.py
pycompilerx/parsing/lexer.py
pycompilerx/parsing/parser.py
pycompilerx-0.1.0.dist-info/licenses/LICENSE
pycompilerx-0.1.0.dist-info/METADATA
pycompilerx-0.1.0.dist-info/WHEEL
pycompilerx-0.1.0.dist-info/entry_points.txt
pycompilerx-0.1.0.dist-info/top_level.txt
pycompilerx-0.1.0.dist-info/RECORD
