Metadata-Version: 2.4
Name: PyCompilerX
Version: 0.1.0
Summary: A Comprehensive Python Compiler Toolkit
Author-email: PyCompilerX Team <contact@pycompilerx.dev>
Maintainer-email: PyCompilerX Team <contact@pycompilerx.dev>
License: MIT
Project-URL: Homepage, https://github.com/pycompilerx/pycompilerx
Project-URL: Documentation, https://pycompilerx.readthedocs.io
Project-URL: Repository, https://github.com/pycompilerx/pycompilerx
Project-URL: Bug Tracker, https://github.com/pycompilerx/pycompilerx/issues
Project-URL: Changelog, https://github.com/pycompilerx/pycompilerx/blob/main/CHANGELOG.md
Project-URL: Source Code, https://github.com/pycompilerx/pycompilerx
Keywords: compiler,ast,parsing,code-generation,optimization,python,llvm,cython,numba,static-analysis,jit
Classifier: Development Status :: 4 - Beta
Classifier: Intended Audience :: Developers
Classifier: Intended Audience :: Education
Classifier: License :: OSI Approved :: MIT License
Classifier: Operating System :: OS Independent
Classifier: Programming Language :: Python :: 3
Classifier: Programming Language :: Python :: 3.8
Classifier: Programming Language :: Python :: 3.9
Classifier: Programming Language :: Python :: 3.10
Classifier: Programming Language :: Python :: 3.11
Classifier: Programming Language :: Python :: 3.12
Classifier: Topic :: Software Development :: Compilers
Classifier: Topic :: Software Development :: Code Generators
Classifier: Topic :: Software Development :: Libraries :: Python Modules
Classifier: Topic :: Education
Classifier: Topic :: Scientific/Engineering
Requires-Python: >=3.8
License-File: LICENSE
Requires-Dist: typing-extensions>=4.0.0; python_version < "3.10"
Provides-Extra: full
Requires-Dist: ply>=3.11; extra == "full"
Requires-Dist: lark>=1.1.0; extra == "full"
Requires-Dist: gast>=0.5.0; extra == "full"
Requires-Dist: llvmlite>=0.40.0; python_version >= "3.8" and extra == "full"
Requires-Dist: cython>=0.29.0; extra == "full"
Requires-Dist: numba>=0.57.0; python_version >= "3.8" and extra == "full"
Requires-Dist: mypy>=1.0.0; extra == "full"
Requires-Dist: astor>=0.8.0; python_version < "3.9" and extra == "full"
Provides-Extra: dev
Requires-Dist: pytest>=7.0.0; extra == "dev"
Requires-Dist: pytest-cov>=4.0.0; extra == "dev"
Requires-Dist: black>=22.0.0; extra == "dev"
Requires-Dist: flake8>=5.0.0; extra == "dev"
Requires-Dist: mypy>=1.0.0; extra == "dev"
Requires-Dist: pre-commit>=2.20.0; extra == "dev"
Provides-Extra: docs
Requires-Dist: sphinx>=5.0.0; extra == "docs"
Requires-Dist: sphinx-rtd-theme>=1.0.0; extra == "docs"
Requires-Dist: myst-parser>=0.18.0; extra == "docs"
Dynamic: license-file
